omakase_media_tools/__init__.py
omakase_media_tools/audio_metrics.py
omakase_media_tools/mediainfo.py
omakase_media_tools/omt.py
omakase_media_tools/player_json.py
omakase_media_tools/thumbnails.py
omakase_media_tools/video_bitrate.py
omakase_media_tools/waveforms.py
omakase_media_tools/docs/dolby_hybrik_job.md
omakase_media_tools/docs/mediaconvert_job.md
omakase_media_tools/docs/omakase_player_hls_media.md
omakase_media_tools/docs/omakase_player_json.md
omakase_media_tools/docs/omt.md
omakase_media_tools/docs/tears_of_steel_source_media.md
omakase_media_tools/file_log/__init__.py
omakase_media_tools/file_log/logger.py
omakase_media_tools/media/template.json
omakase_media_tools/media/tears-of-steel/tears-of-steel_24fps.json
omakase_media_tools/media/tears-of-steel/analysis/audio-poi.vtt
omakase_media_tools/media/tears-of-steel/analysis/dialog.vtt
omakase_media_tools/media/tears-of-steel/analysis/program-poi.vtt
omakase_media_tools/media/tears-of-steel/analysis/program-scenes.vtt
omakase_media_tools/media/tears-of-steel/analysis/tears-of-steel_sdr_BITC_EN_20_R128_2-SEC.vtt
omakase_media_tools/media/tears-of-steel/analysis/tears-of-steel_sdr_BITC_EN_20_RMS_2-SEC.vtt
omakase_media_tools/media/tears-of-steel/analysis/tearsofsteel_4k_2-SEC.vtt
omakase_media_tools/media/tears-of-steel/thumbnails/tearsofsteel_4k00002.jpg
omakase_media_tools/media/tears-of-steel/thumbnails/thumbnails.vtt
omakase_media_tools/media/tears-of-steel/waveforms/tears-of-steel_EN_20_L.vtt
omakase_media_tools/media/tears-of-steel/waveforms/tears-of-steel_EN_20_R.vtt
omakase_media_tools/mediaconvert/tears-of-steel.m3u8
omakase_media_tools/mediaconvert/tears-of-steel_sdr_24_BITC.json
omakase_media_tools/mediaconvert/tears-of-steel_sdr_24_BITC_by-channels.json
omakase_media_tools-0.1.16.dist-info/LICENSE
omakase_media_tools-0.1.16.dist-info/METADATA
omakase_media_tools-0.1.16.dist-info/WHEEL
omakase_media_tools-0.1.16.dist-info/entry_points.txt
omakase_media_tools-0.1.16.dist-info/top_level.txt
omakase_media_tools-0.1.16.dist-info/RECORD
