Metadata-Version: 2.1
Name: omakase-media-tools
Version: 0.1.16
Summary: A CLI utility and samples for creation of sample media and temporal metadata tracks for use with the Omakase Player framework
Author-email: ByOmakase <info@byomakase.org>
License: Apache License 2.0
Project-URL: Homepage, https://github.com/byomakase/omakase-player
Classifier: Programming Language :: Python :: 3
Classifier: License :: OSI Approved :: Apache Software License
Classifier: Operating System :: OS Independent
Requires-Python: >=3.6
License-File: LICENSE
Requires-Dist: ffmpeg-python
Requires-Dist: ffmpeg-bitrate-stats
